cloudmesh_vagrant/__init__.py
cloudmesh_vagrant/cm_vbox.py
cloudmesh_vagrant/version.py
cloudmesh_vagrant/image/__init__.py
cloudmesh_vagrant/image/image.py
cloudmesh_vagrant/vm/__init__.py
cloudmesh_vagrant/vm/vm.py
cloudmesh_vagrant-1.2.2.dist-info/DESCRIPTION.rst
cloudmesh_vagrant-1.2.2.dist-info/METADATA
cloudmesh_vagrant-1.2.2.dist-info/RECORD
cloudmesh_vagrant-1.2.2.dist-info/WHEEL
cloudmesh_vagrant-1.2.2.dist-info/entry_points.txt
cloudmesh_vagrant-1.2.2.dist-info/metadata.json
cloudmesh_vagrant-1.2.2.dist-info/top_level.txt
