Metadata-Version: 2.0
Name: cloudmesh-vagrant
Version: 1.2.2
Summary: cloudmesh_vagrant - A real simple interface to virtualbox via vagrant
Home-page: https://github.com/cloudmesh/cloudmesh_vagrant
Author: Gregor von Laszewski
Author-email: laszewski@gmail.com
License: Apache License, Version 2.0
Keywords: cloud cmd commandshell plugins cloudmesh vagrant virtualbox
Platform: UNKNOWN
Classifier: Intended Audience :: Developers
Classifier: Intended Audience :: Education
Classifier: Intended Audience :: Science/Research
Classifier: Development Status :: 5 - Production/Stable
Classifier: Intended Audience :: Developers
Classifier: License :: OSI Approved :: Apache Software License
Classifier: Operating System :: MacOS :: MacOS X
Classifier: Operating System :: POSIX :: Linux
Classifier: Programming Language :: Python :: 2.7
Classifier: Topic :: Scientific/Engineering
Classifier: Topic :: System :: Clustering
Classifier: Topic :: System :: Distributed Computing
Classifier: Topic :: Software Development :: Libraries :: Python Modules
Classifier: Environment :: Console
Requires-Dist: cloudmesh-client
